simplyplot.py
simplyplot-0.2.dist-info/DESCRIPTION.rst
simplyplot-0.2.dist-info/METADATA
simplyplot-0.2.dist-info/RECORD
simplyplot-0.2.dist-info/WHEEL
simplyplot-0.2.dist-info/metadata.json
simplyplot-0.2.dist-info/top_level.txt
