Metadata-Version: 2.0
Name: simplyplot
Version: 0.2
Summary: A Python wrapper around Matplotlib, create basic charts with less lines of codes.
Home-page: UNKNOWN
Author: Marcus Flodihn
Author-email: marcus.flodihn@gmail.com
License: MIT
Platform: UNKNOWN
Requires-Dist: matplotlib
